webpush/__init__.py
webpush/cli.py
webpush/types.py
webpush/vapid.py
webpush-1.0.4.dist-info/METADATA
webpush-1.0.4.dist-info/WHEEL
webpush-1.0.4.dist-info/entry_points.txt
webpush-1.0.4.dist-info/licenses/LICENSE
webpush-1.0.4.dist-info/RECORD
