Metadata-Version: 2.4
Name: webpush
Version: 1.0.4
Summary: WebPush library for python
Project-URL: Homepage, https://github.com/delvinru/webpush-py
Project-URL: Repository, https://github.com/delvinru/webpush-py
Author-email: Alexey <delvinru@gmail.com>
License-Expression: MIT
License-File: LICENSE
Keywords: pwa,pydantic,webpush
Requires-Python: ~=3.10
Requires-Dist: cryptography>=44.0.0
Requires-Dist: email-validator>=2.2.0
Requires-Dist: pydantic>=2.10.5
Requires-Dist: pyjwt>=2.10.1
